aicoding_backend/__init__.py
aicoding_backend/main.py
aicoding_backend/notebooks/agent.ipynb
aicoding_backend/prompts/CreateFeatureProjectRules.md
aicoding_backend/prompts/__init__.py
aicoding_backend/prompts/init_project_rules.py
aicoding_backend/prompts/init_requirements_doc.py
aicoding_backend/prompts/java_design_doc_template.md
aicoding_backend/prompts/java_implementation_template.md
aicoding_backend/prompts/java_test_controller.md
aicoding_backend/prompts/java_test_repo.md
aicoding_backend/prompts/java_test_service.md
aicoding_backend/prompts/prp_base.md
aicoding_backend/tools/__init__.py
aicoding_backend/tools/generate_test.py
aicoding_backend/tools/init_project_rules.py
aicoding_backend/tools/init_requirements_doc.py
aicoding_backend/tools/skills_expert.py
aicoding_backend/utils/__init__.py
aicoding_backend/utils/file_reader.py
aicoding_backend/utils/file_utils.py
aicoding_backend/utils/git_info.py
aicoding_backend/utils/loader.py
aicoding_backend/utils/log.py
aicoding_backend/utils/template.py
aicoding_backend/utils/user_info.py
aicoding_backend/utils/version.py
aicoding_backend-0.1.16.dist-info/METADATA
aicoding_backend-0.1.16.dist-info/WHEEL
aicoding_backend-0.1.16.dist-info/entry_points.txt
aicoding_backend-0.1.16.dist-info/licenses/LICENSE
aicoding_backend-0.1.16.dist-info/RECORD
