Metadata-Version: 2.4
Name: aicoding-backend
Version: 0.1.16
Summary: AI Coding Backend - A backend service for AI-assisted coding with MCP (Model Context Protocol) integration
Project-URL: Homepage, https://github.com/yourusername/aicoding-backend
Project-URL: Documentation, https://github.com/yourusername/aicoding-backend#readme
Project-URL: Repository, https://github.com/yourusername/aicoding-backend
Project-URL: Issues, https://github.com/yourusername/aicoding-backend/issues
Author-email: Chen Shuren <csrrrr@whut.edu.com>
License: MIT
License-File: LICENSE
Keywords: ai,backend,code-generation,coding,mcp
Classifier: Development Status :: 3 - Alpha
Classifier: Intended Audience :: Developers
Classifier: License :: OSI Approved :: MIT License
Classifier: Programming Language :: Python :: 3
Classifier: Programming Language :: Python :: 3.13
Classifier: Topic :: Software Development :: Libraries :: Python Modules
Requires-Python: >=3.13
Requires-Dist: gitpython>=3.1.45
Requires-Dist: httpx>=0.28.1
Requires-Dist: keyring>=25.6.0
Requires-Dist: mcp[cli]>=1.18.0
Requires-Dist: pipx>=1.8.0
Requires-Dist: pydantic>=2.0.0
